{"cameraMode":{"drawMode":0,"name":"Shaded","section":"Shading Mode"},"sceneLighting":true,"audioPlay":false,"sceneViewState":{"m_AlwaysRefresh":false,"showFog":true,"showSkybox":true,"showFlares":true,"showImageEffects":true,"showParticleSystems":true,"showVisualEffectGraphs":true,"m_FxEnabled":true},"in2DMode":false,"pivot":{"x":-3.7794699668884279,"y":85.0792465209961,"z":-14.939436912536621},"rotation":{"x":0.04546992480754852,"y":-0.5719041228294373,"z":0.03177378326654434,"w":0.8184472918510437},"size":216.05450439453126,"orthographic":false}